[{"temp": 5.3, "description": "Clear", "city": "Tokyo", "time": "2025-02-23 17:36:05"}, {"temp": -1.5, "description": "Sunny", "city": "Delhi", "time": "2025-02-23 17:36:05"}, {"temp": 4.3, "description": "Clear", "city": "Shanghai", "time": "2025-02-23 17:36:05"}, {"temp": 32.3, "description": "Overcast", "city": "Mumbai", "time": "2025-02-23 17:36:05"}, {"temp": -1.9, "description": "Clear", "city": "Beijing", "time": "2025-02-23 17:36:05"}, {"temp": 23.7, "description": "Patchy rain nearby", "city": "Dhaka", "time": "2025-02-23 17:36:05"}, {"code": 500, "message": "Missing expected key: 'current'", "city": "Osaka", "time": "2025-02-23 17:36:05"}, {"temp": 24.1, "description": "Mist", "city": "Karachi", "time": "2025-02-23 17:36:05"}, {"temp": 9.0, "description": "Overcast", "city": "Chongqing", "time": "2025-02-23 17:36:05"}, {"temp": 1.2, "description": "Partly cloudy", "city": "Istanbul", "time": "2025-02-23 17:36:05"}, {"code": 500, "message": "Missing expected key: 'current'", "city": "Kolkata", "time": "2025-02-23 17:36:05"}, {"temp": 0.3, "description": "Clear", "city": "Tianjin", "time": "2025-02-23 17:36:05"}, {"temp": 13.2, "description": "Overcast", "city": "Guangzhou", "time": "2025-02-23 17:36:05"}, {"temp": 15.2, "description": "Partly cloudy", "city": "Shenzhen", "time": "2025-02-23 17:36:05"}, {"temp": 7.1, "description": "Light rain", "city": "Chengdu", "time": "2025-02-23 17:36:05"}, {"temp": 31.4, "description": "Partly cloudy", "city": "Bangkok", "time": "2025-02-23 17:36:05"}, {"temp": 19.3, "description": "Clear", "city": "Riyadh", "time": "2025-02-23 17:36:05"}, {"temp": 27.4, "description": "Partly cloudy", "city": "Jakarta", "time": "2025-02-23 17:36:05"}, {"temp": -5.8, "description": "Clear", "city": "Seoul", "time": "2025-02-23 17:36:05"}, {"temp": 16.1, "description": "Partly cloudy", "city": "Hong Kong", "time": "2025-02-23 17:36:05"}, {"temp": 7.1, "description": "Light rain", "city": "Chengdu", "time": "2025-02-23 17:36:05"}, {"temp": 15.2, "description": "Partly cloudy", "city": "Shenzhen", "time": "2025-02-23 17:36:05"}, {"temp": 27.4, "description": "Clear", "city": "Ho Chi Minh City", "time": "2025-02-23 17:36:05"}, {"temp": 27.4, "description": "Partly cloudy", "city": "Jakarta", "time": "2025-02-23 17:36:05"}, {"temp": 26.2, "description": "Light rain", "city": "Kuala Lumpur", "time": "2025-02-23 17:36:05"}, {"temp": 19.3, "description": "Clear", "city": "Riyadh", "time": "2025-02-23 17:36:05"}, {"temp": -1.4, "description": "Clear", "city": "Jinan", "time": "2025-02-23 17:36:05"}, {"temp": 15.2, "description": "Partly cloudy", "city": "Shenzhen", "time": "2025-02-23 17:36:05"}, {"temp": 7.1, "description": "Light rain", "city": "Chengdu", "time": "2025-02-23 17:36:05"}, {"temp": 15.4, "description": "Overcast", "city": "Hanoi", "time": "2025-02-23 17:36:05"}]